message_listener/__init__.py
message_listener/handler_debug.py
message_listener/server.py
message_listener/abstract/__init__.py
message_listener/abstract/handler_interface.py
message_listener-1.1.0.dist-info/LICENSE
message_listener-1.1.0.dist-info/METADATA
message_listener-1.1.0.dist-info/WHEEL
message_listener-1.1.0.dist-info/top_level.txt
message_listener-1.1.0.dist-info/RECORD
