Metadata-Version: 2.1
Name: message-listener
Version: 1.1.0
Summary: Server listener and iot_message handler
Home-page: https://github.com/bkosciow/message_listener
Author: Bartosz Kościów
Author-email: kosci1@gmail.com
License: MIT
Keywords: iot_message,raspberry pi
Platform: UNKNOWN
Classifier: Development Status :: 4 - Beta
Classifier: Environment :: Console
Classifier: Intended Audience :: Developers
Classifier: Natural Language :: English
Classifier: License :: OSI Approved :: MIT License
Classifier: Operating System :: OS Independent
Classifier: Programming Language :: Python
Classifier: Programming Language :: Python :: 3
Classifier: Topic :: Software Development :: Libraries :: Python Modules
Classifier: Topic :: Home Automation
Requires-Dist: iot-message
